Car.py
MyPythonProject-1.0.dist-info/METADATA
MyPythonProject-1.0.dist-info/WHEEL
MyPythonProject-1.0.dist-info/top_level.txt
MyPythonProject-1.0.dist-info/RECORD
