Metadata-Version: 2.1
Name: MyPythonProject
Version: 1.0
Summary: Test Python
Home-page: https://google.com
Author: deepak
Author-email: dd@dd.com
License: Free
Platform: UNKNOWN
